odoo/addons/purchase_batch_invoicing/README.rst
odoo/addons/purchase_batch_invoicing/__init__.py
odoo/addons/purchase_batch_invoicing/__manifest__.py
odoo/addons/purchase_batch_invoicing/data/ir_cron_data.xml
odoo/addons/purchase_batch_invoicing/i18n/am.po
odoo/addons/purchase_batch_invoicing/i18n/ar.po
odoo/addons/purchase_batch_invoicing/i18n/bg.po
odoo/addons/purchase_batch_invoicing/i18n/bs.po
odoo/addons/purchase_batch_invoicing/i18n/ca.po
odoo/addons/purchase_batch_invoicing/i18n/ca_ES.po
odoo/addons/purchase_batch_invoicing/i18n/cs.po
odoo/addons/purchase_batch_invoicing/i18n/da.po
odoo/addons/purchase_batch_invoicing/i18n/de.po
odoo/addons/purchase_batch_invoicing/i18n/el_GR.po
odoo/addons/purchase_batch_invoicing/i18n/en_AU.po
odoo/addons/purchase_batch_invoicing/i18n/en_GB.po
odoo/addons/purchase_batch_invoicing/i18n/es.po
odoo/addons/purchase_batch_invoicing/i18n/es_AR.po
odoo/addons/purchase_batch_invoicing/i18n/es_CL.po
odoo/addons/purchase_batch_invoicing/i18n/es_CO.po
odoo/addons/purchase_batch_invoicing/i18n/es_CR.po
odoo/addons/purchase_batch_invoicing/i18n/es_DO.po
odoo/addons/purchase_batch_invoicing/i18n/es_EC.po
odoo/addons/purchase_batch_invoicing/i18n/es_ES.po
odoo/addons/purchase_batch_invoicing/i18n/es_MX.po
odoo/addons/purchase_batch_invoicing/i18n/es_PE.po
odoo/addons/purchase_batch_invoicing/i18n/es_PY.po
odoo/addons/purchase_batch_invoicing/i18n/es_VE.po
odoo/addons/purchase_batch_invoicing/i18n/et.po
odoo/addons/purchase_batch_invoicing/i18n/eu.po
odoo/addons/purchase_batch_invoicing/i18n/fa.po
odoo/addons/purchase_batch_invoicing/i18n/fi.po
odoo/addons/purchase_batch_invoicing/i18n/fr.po
odoo/addons/purchase_batch_invoicing/i18n/fr_CA.po
odoo/addons/purchase_batch_invoicing/i18n/fr_CH.po
odoo/addons/purchase_batch_invoicing/i18n/fr_FR.po
odoo/addons/purchase_batch_invoicing/i18n/gl.po
odoo/addons/purchase_batch_invoicing/i18n/gl_ES.po
odoo/addons/purchase_batch_invoicing/i18n/he.po
odoo/addons/purchase_batch_invoicing/i18n/hi.po
odoo11_addon_purchase_batch_invoicing-11.0.1.1.0.dist-info/METADATA
odoo11_addon_purchase_batch_invoicing-11.0.1.1.0.dist-info/WHEEL
odoo11_addon_purchase_batch_invoicing-11.0.1.1.0.dist-info/top_level.txt
odoo11_addon_purchase_batch_invoicing-11.0.1.1.0.dist-info/RECORD
